eurovat/__init__.py
eurovat/cn_code.py
eurovat/functions.py
eurovat/rate.py
eurovat/registry.py
eurovat/states.py
eurovat/tedb.py
eurovat/vat_number.py
eurovat/cache/__init__.py
eurovat/cache/cache.py
eurovat/cache/django.py
eurovat/cache/filesystem.py
eurovat/data/__init__.py
eurovat/data/vat_rules.json
eurovat/data/vies.xml
eurovat-0.9.5.dist-info/METADATA
eurovat-0.9.5.dist-info/WHEEL
eurovat-0.9.5.dist-info/top_level.txt
eurovat-0.9.5.dist-info/RECORD
