Metadata-Version: 2.1
Name: eurovat
Version: 0.9.5
Summary: A python library to get the vat right in the EU.
Home-page: https://github.com/airgproducts/eurovat
Author: airG products
Author-email: hello@airgproducts.com
License: MIT License
Keywords: vat,eu,tax
Platform: UNKNOWN
Classifier: Programming Language :: Python :: 3
Requires-Dist: requests
Requires-Dist: pycountry
